routeml/__init__.py
routeml/cvrp.py
routeml/draw.py
routeml/solvers.py
routeml/utils.py
tests/__init__.py
tests/test_cvrp.py
tests/integration/__init__.py
tests/integration/test_draw_integration.py
tests/integration/test_vrplib_cost_integration.py
tests/unit/__init__.py
tests/unit/draw/__init__.py
tests/unit/draw/test_draw_histogram_heatmap.py
tests/unit/utils/__init__.py
tests/unit/utils/test_get_cvrp_cost.py
tests/unit/utils/test_get_graph_embedding.py
tests/unit/utils/test_get_is_feasible.py
tests/unit/utils/test_get_logit_mask.py
tests/unit/utils/test_get_route_demand.py
tests/unit/utils/test_montreal_canonical.py
tests/unit/utils/test_pad_matrices.py
tests/unit/utils/test_parse_vrplib_file.py
tests/unit/utils/test_parse_vrplib_solution.py
tests/unit/utils/test_rotate_coords.py
tests/unit/utils/test_routes_to_solution.py
tests/unit/utils/test_solution_to_adj_mat.py
tests/unit/utils/test_solution_to_routes.py
routeml-0.24.0.dist-info/METADATA
routeml-0.24.0.dist-info/WHEEL
routeml-0.24.0.dist-info/top_level.txt
routeml-0.24.0.dist-info/RECORD
