Metadata-Version: 2.1
Name: routeml
Version: 0.24.0
Summary: Python package for CVRP utilities
Home-page: https://github.com/jkschin/routeml
Author: Your Name
Author-email: jkschin@mit.edu
Classifier: Development Status :: 3 - Alpha
Classifier: Intended Audience :: Developers
Classifier: License :: OSI Approved :: MIT License
Classifier: Programming Language :: Python :: 3
Classifier: Programming Language :: Python :: 3.7
Classifier: Programming Language :: Python :: 3.8
Classifier: Programming Language :: Python :: 3.9
Requires-Dist: numpy
Requires-Dist: scipy
Requires-Dist: matplotlib
Requires-Dist: hygese
Requires-Dist: colorcet
Requires-Dist: scikit-learn
Requires-Dist: pillow
Requires-Dist: seaborn
